mandelia/util.py
mandelia/__main__.py
mandelia/py.typed
mandelia/__init__.py
mandelia/model/fractale.pyi
mandelia/model/manager.py
mandelia/model/fractale.cpython-38-i386-linux-gnu.so
mandelia/model/__init__.py
mandelia/model/fractale.pyx
mandelia/controller/controller.py
mandelia/controller/__init__.py
mandelia/view/widget.py
mandelia/view/export.py
mandelia/view/wait.py
mandelia/view/view.py
mandelia/view/__init__.py
mandelia/view/images/logo.png
mandelia/view/images/logo.ico
mandelia-0.0.4.dist-info/entry_points.txt
mandelia-0.0.4.dist-info/LICENSE
mandelia-0.0.4.dist-info/top_level.txt
mandelia-0.0.4.dist-info/RECORD
mandelia-0.0.4.dist-info/METADATA
mandelia-0.0.4.dist-info/WHEEL
mandelia.libs/libgomp-65f46eca.so.1.0.0
