Metadata-Version: 2.1
Name: mandelia
Version: 0.0.4
Summary: Application to visualize fractals of mandelbrot and julia.
Home-page: https://github.com/Dashstrom/mandelia
Author: Dashstrom
Author-email: dashstrom.pro@gmail.com
License: GPL-3.0 License
Keywords: mandelbrot,julia,fractale,tkinter
Platform: any
Classifier: License :: OSI Approved :: GNU General Public License v3 (GPLv3)
Classifier: Programming Language :: Cython
Classifier: Programming Language :: Python :: 3
Classifier: Programming Language :: Python :: 3.6
Classifier: Programming Language :: Python :: 3.7
Classifier: Programming Language :: Python :: 3.8
Classifier: Programming Language :: Python :: 3.9
Classifier: Programming Language :: Python :: 3.10
Classifier: Operating System :: Microsoft :: Windows :: Windows 10
Classifier: Operating System :: POSIX :: Linux
Classifier: Operating System :: MacOS
Classifier: Operating System :: OS Independent
Classifier: Natural Language :: French
Requires-Python: >=3.6.0
License-File: LICENSE
Requires-Dist: wheel
Requires-Dist: Cython
Requires-Dist: Pillow
Requires-Dist: PyInstaller
Requires-Dist: typing-extensions ; python_version < "3.10"
Requires-Dist: numpy (==1.21.0) ; python_version <= "3.9" and sys_platform == "darwin" and platform_machine == "arm64"
Requires-Dist: numpy (==1.19.3) ; python_version <= "3.9" and sys_platform == "linux" and platform_machine == "aarch64"
Requires-Dist: numpy (==1.13.3) ; python_version == "3.6" and platform_machine != "aarch64" and platform_machine != "arm64"
Requires-Dist: numpy (==1.14.5) ; python_version == "3.7" and platform_machine != "aarch64" and platform_machine != "arm64"
Requires-Dist: numpy (==1.17.3) ; python_version == "3.8" and platform_machine != "aarch64" and platform_machine != "arm64"
Requires-Dist: numpy (==1.19.3) ; python_version == "3.9" and platform_machine != "aarch64" and platform_machine != "arm64"
Requires-Dist: numpy (==1.22.3) ; python_version >= "3.10"
Requires-Dist: opencv-python (==4.5.5.64) ; sys_platform != "linux" or platform_machine != "i686"
Requires-Dist: opencv-python (==4.5.1.48) ; sys_platform == "linux" and platform_machine == "i686"
